clize/__init__.py
clize/_sphinx.py
clize/converters.py
clize/errors.py
clize/help.py
clize/legacy.py
clize/parameters.py
clize/parser.py
clize/runner.py
clize/util.py
clize/tests/__init__.py
clize/tests/test_converters.py
clize/tests/test_help.py
clize/tests/test_legacy.py
clize/tests/test_legacy_py3k.py
clize/tests/test_parameters.py
clize/tests/test_parser.py
clize/tests/test_runner.py
clize/tests/test_testutil.py
clize/tests/test_util.py
clize/tests/util.py
clize-5.0.2.dist-info/AUTHORS
clize-5.0.2.dist-info/COPYING
clize-5.0.2.dist-info/LICENSE.txt
clize-5.0.2.dist-info/METADATA
clize-5.0.2.dist-info/WHEEL
clize-5.0.2.dist-info/top_level.txt
clize-5.0.2.dist-info/RECORD
