Metadata-Version: 2.1
Name: clize
Version: 5.0.2
Summary: Turn functions into command-line interfaces
Home-page: https://github.com/epsy/clize
Author: Yann Kaiser
Author-email: kaiser.yann@gmail.com
License: MIT
Keywords: CLI,options,arguments,getopts,getopt,argparse,introspection,flags,decorator,subcommands
Classifier: Development Status :: 5 - Production/Stable
Classifier: License :: OSI Approved :: MIT License
Classifier: Programming Language :: Python :: 3
Classifier: Programming Language :: Python :: 3.6
Classifier: Programming Language :: Python :: 3.7
Classifier: Programming Language :: Python :: 3.8
Classifier: Programming Language :: Python :: 3.9
Classifier: Programming Language :: Python :: 3.10
Classifier: Programming Language :: Python :: Implementation :: CPython
Classifier: Programming Language :: Python :: Implementation :: PyPy
Classifier: Environment :: Console
Classifier: Intended Audience :: Developers
Classifier: Intended Audience :: System Administrators
Classifier: Operating System :: OS Independent
Classifier: Topic :: Software Development
Classifier: Topic :: Software Development :: Libraries :: Python Modules
Classifier: Topic :: Software Development :: User Interfaces
Requires-Python: >=3.6
Provides-Extra: datetime
Provides-Extra: test
Provides-Extra: clize-own-docs
License-File: LICENSE.txt
License-File: COPYING
License-File: AUTHORS
